contentfetch/__init__.py
contentfetch/extract_content.py
contentfetch/text.py
contentfetch/newsfetch/__init__.py
contentfetch/newsfetch/google.py
contentfetch/newsfetch/helpers.py
contentfetch/newsfetch/news.py
contentfetch/newsfetch/utils.py
contentfetch/utils/__init__.py
contentfetch/utils/check_process_status.py
contentfetch/utils/crawler.py
contentfetch/utils/initialize.py
contentfetch/utils/mongo.py
contentfetch/utils/utils.py
contentfetch-0.0.5.dist-info/LICENSE
contentfetch-0.0.5.dist-info/METADATA
contentfetch-0.0.5.dist-info/WHEEL
contentfetch-0.0.5.dist-info/top_level.txt
contentfetch-0.0.5.dist-info/RECORD
